{
  "https://4everland.io": {
    "metadata": {
      "time": "2024-02-22T11:37:27.115571985Z",
      "version": "v0.5.0",
      "job_url": "https://github.com/ipfs/public-gateway-checker/actions/runs/8003843850",
      "gateway_url": "https://4everland.io"
    },
    "results": {
      "DNSLink": {
        "pass": 0,
        "fail": 1,
        "skip": 0
      },
      "CORS": {
        "pass": 0,
        "fail": 1,
        "skip": 0
      },
      "JSON-CBOR": {
        "pass": 0,
        "fail": 3,
        "skip": 0
      }
    }
  },
  "https://cf-ipfs.com": {
    "metadata": {
      "time": "2024-02-22T11:37:33.843660545Z",
      "version": "v0.5.0",
      "job_url": "https://github.com/ipfs/public-gateway-checker/actions/runs/8003843850",
      "gateway_url": "https://cf-ipfs.com"
    },
    "results": {
      "DNSLink": {
        "pass": 0,
        "fail": 1,
        "skip": 0
      },
      "CORS": {
        "pass": 0,
        "fail": 1,
        "skip": 0
      },
      "JSON-CBOR": {
        "pass": 0,
        "fail": 3,
        "skip": 0
      }
    }
  },
  "https://cloudflare-ipfs.com": {
    "metadata": {
      "time": "2024-02-22T11:37:33.730374606Z",
      "version": "v0.5.0",
      "job_url": "https://github.com/ipfs/public-gateway-checker/actions/runs/8003843850",
      "gateway_url": "https://cloudflare-ipfs.com"
    },
    "results": {
      "DNSLink": {
        "pass": 0,
        "fail": 1,
        "skip": 0
      },
      "CORS": {
        "pass": 0,
        "fail": 1,
        "skip": 0
      },
      "JSON-CBOR": {
        "pass": 1,
        "fail": 3,
        "skip": 0
      }
    }
  },
  "https://dweb.eu.org": {
    "metadata": {
      "time": "2024-02-22T11:37:28.012134958Z",
      "version": "v0.5.0",
      "job_url": "https://github.com/ipfs/public-gateway-checker/actions/runs/8003843850",
      "gateway_url": "https://dweb.eu.org"
    },
    "results": {
      "DNSLink": {
        "pass": 0,
        "fail": 1,
        "skip": 0
      },
      "CORS": {
        "pass": 0,
        "fail": 1,
        "skip": 0
      },
      "JSON-CBOR": {
        "pass": 0,
        "fail": 3,
        "skip": 0
      }
    }
  },
  "https://dweb.link": {
    "metadata": {
      "time": "2024-02-22T11:37:31.147625579Z",
      "version": "v0.5.0",
      "job_url": "https://github.com/ipfs/public-gateway-checker/actions/runs/8003843850",
      "gateway_url": "https://dweb.link"
    },
    "results": {
      "DNSLink": {
        "pass": 0,
        "fail": 1,
        "skip": 0
      },
      "CORS": {
        "pass": 1,
        "fail": 0,
        "skip": 0
      },
      "JSON-CBOR": {
        "pass": 0,
        "fail": 3,
        "skip": 0
      }
    }
  },
  "https://gateway.pinata.cloud": {
    "metadata": {
      "time": "2024-02-22T11:37:47.163278461Z",
      "version": "v0.5.0",
      "job_url": "https://github.com/ipfs/public-gateway-checker/actions/runs/8003843850",
      "gateway_url": "https://gateway.pinata.cloud"
    },
    "results": {
      "DNSLink": {
        "pass": 0,
        "fail": 1,
        "skip": 0
      },
      "CORS": {
        "pass": 0,
        "fail": 1,
        "skip": 0
      },
      "JSON-CBOR": {
        "pass": 1,
        "fail": 3,
        "skip": 0
      }
    }
  },
  "https://ipfs.eth.aragon.network": {
    "metadata": {
      "time": "2024-02-22T11:40:35.431750583Z",
      "version": "v0.5.0",
      "job_url": "https://github.com/ipfs/public-gateway-checker/actions/runs/8003843850",
      "gateway_url": "https://ipfs.eth.aragon.network"
    },
    "results": {
      "DNSLink": {
        "pass": 0,
        "fail": 2,
        "skip": 0
      },
      "CORS": {
        "pass": 0,
        "fail": 1,
        "skip": 0
      },
      "JSON-CBOR": {
        "pass": 5,
        "fail": 0,
        "skip": 0
      },
      "IPNS": {
        "pass": 0,
        "fail": 3,
        "skip": 0
      },
      "Others": {
        "pass": 3,
        "fail": 3,
        "skip": 0
      },
      "Block-CAR": {
        "pass": 1,
        "fail": 5,
        "skip": 0
      },
      "Tar": {
        "pass": 1,
        "fail": 0,
        "skip": 0
      },
      "UnixFS": {
        "pass": 2,
        "fail": 1,
        "skip": 0
      },
      "Subdomains": {
        "pass": 0,
        "fail": 3,
        "skip": 0
      }
    }
  },
  "https://ipfs.fleek.co": {
    "metadata": {
      "time": "2024-02-22T11:37:43.615782866Z",
      "version": "v0.5.0",
      "job_url": "https://github.com/ipfs/public-gateway-checker/actions/runs/8003843850",
      "gateway_url": "https://ipfs.fleek.co"
    },
    "results": {
      "DNSLink": {
        "pass": 0,
        "fail": 1,
        "skip": 0
      },
      "CORS": {
        "pass": 0,
        "fail": 1,
        "skip": 0
      },
      "JSON-CBOR": {
        "pass": 0,
        "fail": 3,
        "skip": 0
      }
    }
  },
  "https://ipfs.greyh.at": {
    "metadata": {
      "time": "2024-02-22T11:38:00.513488928Z",
      "version": "v0.5.0",
      "job_url": "https://github.com/ipfs/public-gateway-checker/actions/runs/8003843850",
      "gateway_url": "https://ipfs.greyh.at"
    },
    "results": {
      "DNSLink": {
        "pass": 0,
        "fail": 1,
        "skip": 0
      },
      "CORS": {
        "pass": 1,
        "fail": 0,
        "skip": 0
      },
      "JSON-CBOR": {
        "pass": 0,
        "fail": 3,
        "skip": 0
      }
    }
  },
  "https://ipfs.runfission.com": {
    "metadata": {
      "time": "2024-02-22T11:42:02.351322933Z",
      "version": "v0.5.0",
      "job_url": "https://github.com/ipfs/public-gateway-checker/actions/runs/8003843850",
      "gateway_url": "https://ipfs.runfission.com"
    },
    "results": {
      "DNSLink": {
        "pass": 0,
        "fail": 2,
        "skip": 0
      },
      "CORS": {
        "pass": 0,
        "fail": 1,
        "skip": 0
      },
      "JSON-CBOR": {
        "pass": 4,
        "fail": 1,
        "skip": 0
      },
      "IPNS": {
        "pass": 0,
        "fail": 4,
        "skip": 0
      },
      "Others": {
        "pass": 3,
        "fail": 3,
        "skip": 0
      },
      "Block-CAR": {
        "pass": 3,
        "fail": 6,
        "skip": 0
      },
      "Tar": {
        "pass": 1,
        "fail": 0,
        "skip": 0
      },
      "UnixFS": {
        "pass": 2,
        "fail": 1,
        "skip": 0
      },
      "Subdomains": {
        "pass": 0,
        "fail": 3,
        "skip": 0
      }
    }
  },
  "https://nftstorage.link": {
    "metadata": {
      "time": "2024-02-22T11:38:17.731482189Z",
      "version": "v0.5.0",
      "job_url": "https://github.com/ipfs/public-gateway-checker/actions/runs/8003843850",
      "gateway_url": "https://nftstorage.link"
    },
    "results": {
      "DNSLink": {
        "pass": 0,
        "fail": 1,
        "skip": 0
      },
      "CORS": {
        "pass": 0,
        "fail": 1,
        "skip": 0
      },
      "JSON-CBOR": {
        "pass": 0,
        "fail": 3,
        "skip": 0
      }
    }
  },
  "https://permaweb.eu.org": {
    "metadata": {
      "time": "2024-02-22T11:38:22.075243751Z",
      "version": "v0.5.0",
      "job_url": "https://github.com/ipfs/public-gateway-checker/actions/runs/8003843850",
      "gateway_url": "https://permaweb.eu.org"
    },
    "results": {
      "DNSLink": {
        "pass": 0,
        "fail": 1,
        "skip": 0
      },
      "CORS": {
        "pass": 0,
        "fail": 1,
        "skip": 0
      },
      "JSON-CBOR": {
        "pass": 0,
        "fail": 3,
        "skip": 0
      }
    }
  },
  "https://trustless-gateway.link": {
    "metadata": {
      "time": "2024-02-22T11:38:27.656507622Z",
      "version": "v0.5.0",
      "job_url": "https://github.com/ipfs/public-gateway-checker/actions/runs/8003843850",
      "gateway_url": "https://trustless-gateway.link"
    },
    "results": {
      "DNSLink": {
        "pass": 0,
        "fail": 1,
        "skip": 0
      },
      "CORS": {
        "pass": 1,
        "fail": 0,
        "skip": 0
      },
      "JSON-CBOR": {
        "pass": 0,
        "fail": 3,
        "skip": 0
      }
    }
  },
  "https://video.oneloveipfs.com": {
    "metadata": {
      "time": "2024-02-22T11:38:39.741812287Z",
      "version": "v0.5.0",
      "job_url": "https://github.com/ipfs/public-gateway-checker/actions/runs/8003843850",
      "gateway_url": "https://video.oneloveipfs.com"
    },
    "results": {
      "DNSLink": {
        "pass": 0,
        "fail": 1,
        "skip": 0
      },
      "CORS": {
        "pass": 1,
        "fail": 0,
        "skip": 0
      },
      "JSON-CBOR": {
        "pass": 0,
        "fail": 3,
        "skip": 0
      }
    }
  },
  "https://w3s.link": {
    "metadata": {
      "time": "2024-02-22T11:38:35.72558666Z",
      "version": "v0.5.0",
      "job_url": "https://github.com/ipfs/public-gateway-checker/actions/runs/8003843850",
      "gateway_url": "https://w3s.link"
    },
    "results": {
      "DNSLink": {
        "pass": 0,
        "fail": 1,
        "skip": 0
      },
      "CORS": {
        "pass": 0,
        "fail": 1,
        "skip": 0
      },
      "JSON-CBOR": {
        "pass": 0,
        "fail": 3,
        "skip": 0
      }
    }
  }
}
